LICENSE
README.md
setup.py
byterec.egg-info/PKG-INFO
byterec.egg-info/SOURCES.txt
byterec.egg-info/dependency_links.txt
byterec.egg-info/requires.txt
byterec.egg-info/top_level.txt
examples/__init__.py
examples/amazon.py
examples/criteo.py
examples/main.py
examples/taobao.py
torch_ctr/__init__.py
torch_ctr/activation.py
torch_ctr/layers.py
torch_ctr/models/__init__.py
torch_ctr/models/deepfm.py
torch_ctr/models/din.py
torch_ctr/models/widedeep.py