Metadata-Version: 2.1
Name: byterec
Version: 0.0.1
Summary: A Lighting Pytorch Framework for Recommendation System, Easy-to-use and Easy-to-extend.
Home-page: https://github.com/morningsky/Torch-RecHub
Author: Mincai Lai
Author-email: 757387961@qq.com
License: UNKNOWN
Platform: all
Classifier: Intended Audience :: Developers
Classifier: Intended Audience :: Education
Classifier: Intended Audience :: Science/Research
Classifier: Operating System :: OS Independent
Classifier: Programming Language :: Python :: 3
Classifier: Programming Language :: Python :: 3.7
Classifier: Programming Language :: Python :: 3.8
Classifier: Programming Language :: Python :: 3.9
Classifier: Topic :: Scientific/Engineering
Classifier: Topic :: Scientific/Engineering :: Artificial Intelligence
Classifier: Topic :: Software Development :: Libraries
Classifier: Topic :: Software Development :: Libraries :: Python Modules
Classifier: License :: OSI Approved :: MIT License
License-File: LICENSE
